{"nodes": [{"id": "src_aggregators_scraper_ts", "label": "scraper.ts", "file_type": "code", "source_file": "src\\aggregators\\scraper.ts", "source_location": "L1"}, {"id": "scraper_constructor", "label": "constructor()", "file_type": "code", "source_file": "src\\aggregators\\scraper.ts", "source_location": "L10"}, {"id": "scraper_getrandomproxy", "label": "getRandomProxy()", "file_type": "code", "source_file": "src\\aggregators\\scraper.ts", "source_location": "L15"}, {"id": "scraper_getbrowser", "label": "getBrowser()", "file_type": "code", "source_file": "src\\aggregators\\scraper.ts", "source_location": "L20"}, {"id": "scraper_fetchproducts", "label": "fetchProducts()", "file_type": "code", "source_file": "src\\aggregators\\scraper.ts", "source_location": "L33"}, {"id": "scraper_close", "label": "close()", "file_type": "code", "source_file": "src\\aggregators\\scraper.ts", "source_location": "L49"}, {"id": "scraper_meeshoclient", "label": "MeeshoClient", "file_type": "code", "source_file": "src\\aggregators\\scraper.ts", "source_location": "L57"}, {"id": "scraper_meeshoclient_scrapepage", "label": ".scrapePage()", "file_type": "code", "source_file": "src\\aggregators\\scraper.ts", "source_location": "L61"}, {"id": "scraper_cromaclient", "label": "CromaClient", "file_type": "code", "source_file": "src\\aggregators\\scraper.ts", "source_location": "L102"}, {"id": "scraper_cromaclient_scrapepage", "label": ".scrapePage()", "file_type": "code", "source_file": "src\\aggregators\\scraper.ts", "source_location": "L106"}], "edges": [{"source": "src_aggregators_scraper_ts", "target": "playwright", "relation": "imports_from", "confidence": "EXTRACTED", "source_file": "src\\aggregators\\scraper.ts", "source_location": "L1", "weight": 1.0}, {"source": "src_aggregators_scraper_ts", "target": "src_aggregators_base", "relation": "imports_from", "confidence": "EXTRACTED", "source_file": "src\\aggregators\\scraper.ts", "source_location": "L2", "weight": 1.0}, {"source": "src_aggregators_scraper_ts", "target": "src_types", "relation": "imports_from", "confidence": "EXTRACTED", "source_file": "src\\aggregators\\scraper.ts", "source_location": "L3", "weight": 1.0}, {"source": "src_aggregators_scraper_ts", "target": "scraper_constructor", "relation": "contains", "confidence": "EXTRACTED", "source_file": "src\\aggregators\\scraper.ts", "source_location": "L10", "weight": 1.0}, {"source": "src_aggregators_scraper_ts", "target": "scraper_getrandomproxy", "relation": "contains", "confidence": "EXTRACTED", "source_file": "src\\aggregators\\scraper.ts", "source_location": "L15", "weight": 1.0}, {"source": "src_aggregators_scraper_ts", "target": "scraper_getbrowser", "relation": "contains", "confidence": "EXTRACTED", "source_file": "src\\aggregators\\scraper.ts", "source_location": "L20", "weight": 1.0}, {"source": "src_aggregators_scraper_ts", "target": "scraper_fetchproducts", "relation": "contains", "confidence": "EXTRACTED", "source_file": "src\\aggregators\\scraper.ts", "source_location": "L33", "weight": 1.0}, {"source": "src_aggregators_scraper_ts", "target": "scraper_close", "relation": "contains", "confidence": "EXTRACTED", "source_file": "src\\aggregators\\scraper.ts", "source_location": "L49", "weight": 1.0}, {"source": "src_aggregators_scraper_ts", "target": "scraper_meeshoclient", "relation": "contains", "confidence": "EXTRACTED", "source_file": "src\\aggregators\\scraper.ts", "source_location": "L57", "weight": 1.0}, {"source": "scraper_meeshoclient", "target": "scraper_meeshoclient_scrapepage", "relation": "method", "confidence": "EXTRACTED", "source_file": "src\\aggregators\\scraper.ts", "source_location": "L61", "weight": 1.0}, {"source": "src_aggregators_scraper_ts", "target": "scraper_cromaclient", "relation": "contains", "confidence": "EXTRACTED", "source_file": "src\\aggregators\\scraper.ts", "source_location": "L102", "weight": 1.0}, {"source": "scraper_cromaclient", "target": "scraper_cromaclient_scrapepage", "relation": "method", "confidence": "EXTRACTED", "source_file": "src\\aggregators\\scraper.ts", "source_location": "L106", "weight": 1.0}, {"source": "scraper_getbrowser", "target": "scraper_getrandomproxy", "relation": "calls", "confidence": "EXTRACTED", "source_file": "src\\aggregators\\scraper.ts", "source_location": "L22", "weight": 1.0}, {"source": "scraper_fetchproducts", "target": "scraper_getbrowser", "relation": "calls", "confidence": "EXTRACTED", "source_file": "src\\aggregators\\scraper.ts", "source_location": "L34", "weight": 1.0}, {"source": "scraper_fetchproducts", "target": "scraper_cromaclient_scrapepage", "relation": "calls", "confidence": "EXTRACTED", "source_file": "src\\aggregators\\scraper.ts", "source_location": "L42", "weight": 1.0}, {"source": "scraper_fetchproducts", "target": "scraper_close", "relation": "calls", "confidence": "EXTRACTED", "source_file": "src\\aggregators\\scraper.ts", "source_location": "L45", "weight": 1.0}], "raw_calls": [{"caller_nid": "scraper_constructor", "callee": "super", "source_file": "src\\aggregators\\scraper.ts", "source_location": "L11"}, {"caller_nid": "scraper_getrandomproxy", "callee": "floor", "source_file": "src\\aggregators\\scraper.ts", "source_location": "L17"}, {"caller_nid": "scraper_getrandomproxy", "callee": "random", "source_file": "src\\aggregators\\scraper.ts", "source_location": "L17"}, {"caller_nid": "scraper_getbrowser", "callee": "launch", "source_file": "src\\aggregators\\scraper.ts", "source_location": "L23"}, {"caller_nid": "scraper_fetchproducts", "callee": "newContext", "source_file": "src\\aggregators\\scraper.ts", "source_location": "L35"}, {"caller_nid": "scraper_fetchproducts", "callee": "newPage", "source_file": "src\\aggregators\\scraper.ts", "source_location": "L41"}, {"caller_nid": "scraper_meeshoclient_scrapepage", "callee": "encodeURIComponent", "source_file": "src\\aggregators\\scraper.ts", "source_location": "L62"}, {"caller_nid": "scraper_meeshoclient_scrapepage", "callee": "goto", "source_file": "src\\aggregators\\scraper.ts", "source_location": "L63"}, {"caller_nid": "scraper_meeshoclient_scrapepage", "callee": "catch", "source_file": "src\\aggregators\\scraper.ts", "source_location": "L65"}, {"caller_nid": "scraper_meeshoclient_scrapepage", "callee": "waitForSelector", "source_file": "src\\aggregators\\scraper.ts", "source_location": "L65"}, {"caller_nid": "scraper_meeshoclient_scrapepage", "callee": "evaluate", "source_file": "src\\aggregators\\scraper.ts", "source_location": "L67"}, {"caller_nid": "scraper_meeshoclient_scrapepage", "callee": "map", "source_file": "src\\aggregators\\scraper.ts", "source_location": "L82"}, {"caller_nid": "scraper_cromaclient_scrapepage", "callee": "encodeURIComponent", "source_file": "src\\aggregators\\scraper.ts", "source_location": "L107"}, {"caller_nid": "scraper_cromaclient_scrapepage", "callee": "goto", "source_file": "src\\aggregators\\scraper.ts", "source_location": "L108"}, {"caller_nid": "scraper_cromaclient_scrapepage", "callee": "catch", "source_file": "src\\aggregators\\scraper.ts", "source_location": "L110"}, {"caller_nid": "scraper_cromaclient_scrapepage", "callee": "waitForSelector", "source_file": "src\\aggregators\\scraper.ts", "source_location": "L110"}, {"caller_nid": "scraper_cromaclient_scrapepage", "callee": "evaluate", "source_file": "src\\aggregators\\scraper.ts", "source_location": "L112"}, {"caller_nid": "scraper_cromaclient_scrapepage", "callee": "map", "source_file": "src\\aggregators\\scraper.ts", "source_location": "L127"}]}